wam_api/__init__.py
wam_api/interpolator.py
wam_api/lru_cache.py
wam_api/requirements.txt
swpc_wamipe-0.0.3.dist-info/METADATA
swpc_wamipe-0.0.3.dist-info/WHEEL
swpc_wamipe-0.0.3.dist-info/licenses/LICENSE
swpc_wamipe-0.0.3.dist-info/RECORD
