Metadata-Version: 2.3
Name: swpc-wamipe
Version: 0.0.3
Summary: Provides simple APIs to calculate neutral density values using the NOAA Whole Atmosphere Model-Ionosphere Plasmasphere Electrodynamics (WAM-IPE) model
Project-URL: NOAA SWCC Website, https://www.swpc.noaa.gov/
Project-URL: NOAA WAM-IPE Model, https://www.swpc.noaa.gov/products/wam-ipe
Project-URL: App Dev Club LLC, https://appdevclub.com
Author: Atheesh Thirumalairajan, Nand Vinchhi, Samai Patel, Gili Gordiyenko, Anusha Iyer, Varun Kota, Arav Luthra, Scott Chen
License-File: LICENSE
Classifier: License :: Other/Proprietary License
Classifier: Operating System :: OS Independent
Classifier: Programming Language :: Python :: 3
Requires-Python: >=3.8
Requires-Dist: netcdf4
Requires-Dist: numpy
Requires-Dist: requests
Requires-Dist: scipy
